video_edit_mcp/__init__.py
video_edit_mcp/audio_operations.py
video_edit_mcp/download_utils.py
video_edit_mcp/main.py
video_edit_mcp/util_tools.py
video_edit_mcp/utils.py
video_edit_mcp/video_operations.py
video_edit_mcp-0.1.1.dist-info/METADATA
video_edit_mcp-0.1.1.dist-info/WHEEL
video_edit_mcp-0.1.1.dist-info/entry_points.txt
video_edit_mcp-0.1.1.dist-info/licenses/LICENSE
video_edit_mcp-0.1.1.dist-info/RECORD
