Metadata-Version: 2.4
Name: video-edit-mcp
Version: 0.1.1
Summary: A powerful Model Context Protocol server for video editing operations using MoviePy
Project-URL: Homepage, https://github.com/Aditya2755/video-edit-mcp
Project-URL: Documentation, https://github.com/Aditya2755/video-edit-mcp#readme
Project-URL: Repository, https://github.com/Aditya2755/video-edit-mcp.git
Project-URL: Bug Tracker, https://github.com/Aditya2755/video-edit-mcp/issues
Author-email: Aditya_Barasiya <aditya2755@users.noreply.github.com>
License: MIT
License-File: LICENSE
Keywords: ai,claude,editing,mcp,moviepy,server,video,video-processing
Classifier: Development Status :: 4 - Beta
Classifier: Intended Audience :: Developers
Classifier: License :: OSI Approved :: MIT License
Classifier: Programming Language :: Python :: 3
Classifier: Programming Language :: Python :: 3.10
Classifier: Programming Language :: Python :: 3.11
Classifier: Programming Language :: Python :: 3.12
Classifier: Topic :: Multimedia :: Video
Classifier: Topic :: Scientific/Engineering :: Artificial Intelligence
Classifier: Topic :: Software Development :: Libraries :: Application Frameworks
Classifier: Topic :: Software Development :: Libraries :: Python Modules
Requires-Python: >=3.10
Requires-Dist: mcp>=1.12.2
Requires-Dist: moviepy==1.0.3
Requires-Dist: pillow==9.5.0
Requires-Dist: typing-extensions>=4.0.0
Requires-Dist: yt-dlp>=2023.1.6
Provides-Extra: dev
Requires-Dist: black>=22.0; extra == 'dev'
Requires-Dist: flake8>=4.0; extra == 'dev'
Requires-Dist: mypy>=1.0; extra == 'dev'
Requires-Dist: pytest>=7.0; extra == 'dev'
